litestar_psycopg/__init__.py
litestar_psycopg/__metadata__.py
litestar_psycopg/_utils.py
litestar_psycopg/config.py
litestar_psycopg/plugin.py
litestar_psycopg/py.typed
litestar_psycopg-0.1.1.dist-info/METADATA
litestar_psycopg-0.1.1.dist-info/WHEEL
litestar_psycopg-0.1.1.dist-info/licenses/LICENSE
litestar_psycopg-0.1.1.dist-info/RECORD
