Metadata-Version: 2.4
Name: litestar-psycopg
Version: 0.1.1
Summary: Psycopg plugin for Litestar
Project-URL: Issue, https://github.com/kumokage/litestar-psycopg/issues/
Project-URL: Source, https://github.com/kumokage/litestar-psycopg
Author-email: Alex Glushko <alextvrus@gmail.com>
License: Apache-2.0
License-File: LICENSE
Keywords: litestar,psycopg
Classifier: Development Status :: 3 - Alpha
Classifier: Environment :: Web Environment
Classifier: Intended Audience :: Developers
Classifier: Intended Audience :: System Administrators
Classifier: License :: OSI Approved :: MIT License
Classifier: Natural Language :: English
Classifier: Operating System :: OS Independent
Classifier: Programming Language :: Python
Classifier: Programming Language :: Python :: 3.9
Classifier: Programming Language :: Python :: 3.10
Classifier: Programming Language :: Python :: 3.11
Classifier: Programming Language :: Python :: 3.12
Classifier: Programming Language :: Python :: 3.13
Classifier: Topic :: Database
Classifier: Topic :: Database :: Database Engines/Servers
Classifier: Topic :: Software Development
Classifier: Typing :: Typed
Requires-Python: >=3.9
Requires-Dist: litestar>=2.16.0
Requires-Dist: psycopg[binary,pool]>=3.2.7
